PyTaskHelper/__init__.py
PyTaskHelper/date_utils.py
PyTaskHelper/file_utils.py
PyTaskHelper/string_utils.py
PyTaskHelper/validation.py
PyTaskHelper-0.1.dist-info/LICENSE
PyTaskHelper-0.1.dist-info/METADATA
PyTaskHelper-0.1.dist-info/WHEEL
PyTaskHelper-0.1.dist-info/top_level.txt
PyTaskHelper-0.1.dist-info/RECORD
