Metadata-Version: 2.1
Name: PyTaskHelper
Version: 0.1
Summary: A collection of utility functions to simplify common tasks.
Home-page: https://github.com/devandeveloper/PyTaskHelper
Author: Devanarayan
Author-email: devanarayanp259@gmail.com
License: MIT
Classifier: Programming Language :: Python :: 3
Classifier: License :: OSI Approved :: MIT License
Classifier: Operating System :: OS Independent
Requires-Python: >=3.6
License-File: LICENSE
